geoffrey_pyflakes-0.0.1.dist-info/DESCRIPTION.rst
geoffrey_pyflakes-0.0.1.dist-info/RECORD
geoffrey_pyflakes-0.0.1.dist-info/WHEEL
geoffrey_pyflakes-0.0.1.dist-info/top_level.txt
geoffrey_pyflakes-0.0.1.dist-info/metadata.json
geoffrey_pyflakes-0.0.1.dist-info/METADATA
geoffreyplugins/pyflakes.py
geoffreyplugins/__init__.py
geoffreyplugins/pyflakes/main.js
geoffreyplugins/pyflakes/assets/.gitkeep
