Metadata-Version: 2.0
Name: geoffrey-pyflakes
Version: 0.0.1
Summary: pyflakes is a passive checker of Python programs.
Home-page: https://github.com/GeoffreyCI/geoffrey-pyflakes
Author: Roberto Abdelkader Martínez Pérez
Author-email: robertomartinezp@gmail.com
License: UNKNOWN
Platform: UNKNOWN
